nipreps/synthstrip/__init__.py
nipreps/synthstrip/__main__.py
nipreps/synthstrip/_version.py
nipreps/synthstrip/cli.py
nipreps/synthstrip/model.py
nipreps/synthstrip/wrappers/__init__.py
nipreps/synthstrip/wrappers/nipype.py
nipreps/synthstrip/wrappers/pydra.py
nipreps_synthstrip-0.0.1.dist-info/METADATA
nipreps_synthstrip-0.0.1.dist-info/WHEEL
nipreps_synthstrip-0.0.1.dist-info/entry_points.txt
nipreps_synthstrip-0.0.1.dist-info/licenses/LICENSE
nipreps_synthstrip-0.0.1.dist-info/licenses/NOTICE
nipreps_synthstrip-0.0.1.dist-info/RECORD
