Metadata-Version: 2.3
Name: nipreps-synthstrip
Version: 0.0.1
Summary: NiPreps implementation of FreeSurfer's SynthStrip
Project-URL: Homepage, https://github.com/nipreps/synthstrip
Maintainer-email: Nipreps developers <nipreps@gmail.com>
License:                                  Apache License
License-File: LICENSE
License-File: NOTICE
Classifier: Development Status :: 2 - Pre-Alpha
Classifier: Intended Audience :: Developers
Classifier: License :: OSI Approved :: Apache Software License
Classifier: Operating System :: MacOS :: MacOS X
Classifier: Operating System :: POSIX :: Linux
Classifier: Programming Language :: Python :: 3.8
Classifier: Programming Language :: Python :: 3.9
Classifier: Programming Language :: Python :: 3.10
Classifier: Programming Language :: Python :: 3.11
Classifier: Programming Language :: Python :: 3.12
Requires-Python: >=3.8
Requires-Dist: nibabel
Requires-Dist: nitransforms
Requires-Dist: numpy
Requires-Dist: scipy
Requires-Dist: torch>=1.10.2
Provides-Extra: dev
Requires-Dist: hatch; extra == 'dev'
Requires-Dist: ruff; extra == 'dev'
Provides-Extra: nipype
Requires-Dist: nipype; extra == 'nipype'
Provides-Extra: pydra
Requires-Dist: pydra; extra == 'pydra'
Provides-Extra: test
Requires-Dist: pytest; extra == 'test'
